dmsales/__init__.py
dmsales/api_client.py
dmsales/api_operations.py
dmsales/exceptions.py
dmsales/helpers.py
dmsales/endpoints/__init__.py
dmsales/endpoints/contact_card.py
dmsales/endpoints/contacts.py
dmsales/endpoints/events.py
dmsales/endpoints/person.py
dmsales/endpoints/project.py
dmsales/endpoints/search.py
dmsales/endpoints/segment.py
dmsales/endpoints/techscopeapi.py
dmsales/endpoints/user.py
dmsales/endpoints/validation.py
dmsales-0.2.6.dist-info/METADATA
dmsales-0.2.6.dist-info/WHEEL
dmsales-0.2.6.dist-info/top_level.txt
dmsales-0.2.6.dist-info/RECORD
